meet_man/__init__.py
meet_man/main.py
meet_man-0.1.4.dist-info/entry_points.txt
meet_man-0.1.4.dist-info/LICENSE
meet_man-0.1.4.dist-info/WHEEL
meet_man-0.1.4.dist-info/METADATA
meet_man-0.1.4.dist-info/RECORD
