Metadata-Version: 2.1
Name: meet-man
Version: 0.1.4
Summary: Google Meet Client
Home-page: https://github.com/arghyagod-coder/meet-man
License: MIT
Keywords: meet,meetman,google meet,google-meet-client
Author: Arghya Sarkar
Author-email: arghyasarkar.joker@gmail.com
Requires-Python: >=3.9,<4.0
Classifier: License :: OSI Approved :: MIT License
Classifier: Operating System :: OS Independent
Classifier: Programming Language :: Python :: 3
Classifier: Programming Language :: Python :: 3.6
Classifier: Programming Language :: Python :: 3.7
Classifier: Programming Language :: Python :: 3.8
Classifier: Programming Language :: Python :: 3.9
Requires-Dist: PyQt5 (>=5.15.4,<6.0.0)
Requires-Dist: PyQtWebEngine (>=5.15.4,<6.0.0)
Project-URL: Repository, https://github.com/arghyagod-coder/meet-man
